{"type": "Feature", "id": 12512589, "properties": {"woe:id": 12512589, "woe:parent_id": 552282, "woe:name": "Billund Airport", "woe:placetype": 14, "woe:placetype_name": "Airport", "woe:lang": "ENG", "iso:country": "DK", "meta:provider": ["geoplanet:7.3.1", "geoplanet:7.3.2", "geoplanet:7.4.0", "geoplanet:7.4.1", "geoplanet:7.5.1", "geoplanet:7.5.2", "geoplanet:7.6.0", "geoplanet:7.8.1", "geoplanet:7.9.0", "geoplanet:7.10.0", "geoplanet:8.0.0", "woeplanet:8.0.0"], "meta:indexed": "2020-08-20T20:48:57.071318", "woe:alias_DAN_Q": ["Billund Lufthavn"], "woe:alias_ENG_V": ["BLL", "BLL Airport"], "woe:alias_FRE_Q": ["A\u00e9roport de Billund"], "woe:alias_CZE_Q": ["Letiste Billund"], "woe:alias_FIN_Q": ["Billundin Lentoasema"], "woe:alias_DAN_V": ["BLL Lufthavn"], "woe:alias_SWE_Q": ["Billund Flygplats"], "woe:alias_UNK_Q": ["Letisko Billund"], "woe:alias_DUT_Q": ["Luchthaven Billund"], "woe:alias_GER_Q": ["Flughafen Billund"], "meta:updated": "2020-08-22T03:00:22.804667", "woe:alias_ITA_Q": ["Aeroporto di Billund"], "woe:alias_SPA_Q": ["Aeropuerto de Billund"], "woe:alias_FRE_S": ["Aeroport de Billund"], "woe:alias_POR_Q": ["Aeroporto de Billund"], "woe:hierarchy": {"continent": 24865675, "country": 23424796, "town": 0, "planet": 1, "county": 12582750, "suburb": 0, "state": 28362581, "region": 0, "localadmin": 0}, "woe:timezone_id": 28350895, "woe:hash": "u1yt0hmjq72n", "woe:centroid": [9.14776, 55.746922], "geom:latitude": 55.746922, "geom:longitude": 9.14776, "geom:hash": "u1yt0hmjq72n", "woe:latitude": 55.746922, "geom:centroid": [9.14776, 55.746922], "woe:longitude": 9.14776, "woe:repo": "woeplanet-airport-dk"}, "geometry": {"coordinates": [9.14776, 55.746922], "type": "Point"}}